speedster/__init__.py
speedster/root_op.py
speedster/speedster.py
speedster/utils.py
speedster/api/__init__.py
speedster/api/functions.py
speedster/api/tests/__init__.py
speedster/api/tests/test_huggingface.py
speedster/api/tests/test_onnx.py
speedster/api/tests/test_pytorch.py
speedster/api/tests/test_tensorflow.py
speedster/api/tests/utils.py
speedster/tests/__init__.py
speedster/tests/test_root_op.py
speedster-0.4.0.dist-info/METADATA
speedster-0.4.0.dist-info/WHEEL
speedster-0.4.0.dist-info/top_level.txt
speedster-0.4.0.dist-info/RECORD
