Metadata-Version: 2.1
Name: speedster
Version: 0.4.0
Requires-Dist: nebullvm (>=0.9.0)
Requires-Dist: tabulate (>=0.8.0)
